py_app_pilot/__init__.py
py_app_pilot/py_app_pilot.py
py_app_pilot/resources/author_rc.py
py_app_pilot/resources/logo_rc.py
py_app_pilot/utils/database.py
py_app_pilot/utils/eunm.py
py_app_pilot/utils/log_util.py
py_app_pilot-1.0.2.dist-info/licenses/LICENSE
py_app_pilot-1.0.2.dist-info/METADATA
py_app_pilot-1.0.2.dist-info/WHEEL
py_app_pilot-1.0.2.dist-info/top_level.txt
py_app_pilot-1.0.2.dist-info/RECORD
