Metadata-Version: 2.4
Name: py-app-pilot
Version: 1.0.2
Summary: PyPilot - A powerful Python application management tool with GUI interface, supporting app lifecycle management, process monitoring, log viewing, and environment configuration
Requires-Python: >=3.10
License-File: LICENSE
Requires-Dist: PyQt5>=5.15.0
Requires-Dist: psutil>=5.9.0
Requires-Dist: sqlalchemy>=2.0.0
Requires-Dist: loguru
Dynamic: license-file
